llama_index/py.typed
llama_index/vector_stores/pinecone/__init__.py
llama_index/vector_stores/pinecone/base.py
llama_index/vector_stores/pinecone/utils.py
llama_index_vector_stores_pinecone-0.7.0.dist-info/METADATA
llama_index_vector_stores_pinecone-0.7.0.dist-info/WHEEL
llama_index_vector_stores_pinecone-0.7.0.dist-info/licenses/LICENSE
llama_index_vector_stores_pinecone-0.7.0.dist-info/RECORD
